[
    {
      "category": "DELL Laptops",
      "items": [
        {
          "id": 1,
          "brand": "Dell",
          "itemName": "Latitude X",
          "imageSrc": "../src/assets/img/laptops.jpg",
          "price": 200000,
          "condition": "New",
          "capacity": "512GB",
          "graphics-card": "NVIDIA GeForce GTX 1660 Ti",
          "operating-system": "Windows 11",
          "touchscreen": false,
          "description": "Lorem ipsum dolor sit amet, consectetur adipiscing elit.",
          "model": "Latitude X",
          "ram": "16GB",
          "processor": "Intel Core i7",
          "display-size": "15.6 inches",
          "storage-type": "SSD",
          "colour": "Silver",
          "frame-material": "Aluminum",
          "title": "High-Performance Laptop",
          "location": "Uyo",
          "availability": true,
          "pay-on-delivery": true,
          "fingerprint": true,
          "seller-id": "192934656",
          "seller-phone-no": "+81234567890",
          "battery-life": "8 hours"
        },
        {
            "id": 2,
            "brand": "Dell",
            "itemName": "Latitude Y",
            "imageSrc": "../src/assets/img/laptops.jpg",
            "price": 400000,
            "condition": "New",
            "capacity": "512GB",
            "graphics-card": "NVIDIA GeForce GTX 1660 Ti",
            "operating-system": "Windows 11",
            "touchscreen": true,
            "description": "Lorem ipsum dolor sit amet, consectetur adipiscing elit.",
            "model": "Latitude X",
            "ram": "16GB",
            "processor": "Intel Core i7",
            "display-size": "15.6 inches",
            "storage-type": "SSD",
            "colour": "black",
            "frame-material": "plastic",
            "title": "High-Performance Laptop",
            "location": "Uyo",
            "availability": true,
            "pay-on-delivery": true,
            "fingerprint": true,
            "seller-id": "192934656",
            "seller-phone-no": "+81234567890",
            "battery-life": "12 hours"
          },
          {
            "id": 3,
            "brand": "Dell",
            "itemName": "Latitude X",
            "imageSrc": "../src/assets/img/laptops.jpg",
            "price": 500000,
            "condition": "New",
            "capacity": "512GB",
            "graphics-card": "NVIDIA GeForce GTX 1660 Ti",
            "operating-system": "Windows 11",
            "touchscreen": false,
            "description": "Lorem ipsum dolor sit amet, consectetur adipiscing elit.",
            "model": "Latitude Z",
            "ram": "16GB",
            "processor": "Intel Core i7",
            "display-size": "15.6 inches",
            "storage-type": "SSD",
            "colour": "Silver",
            "frame-material": "Aluminum",
            "title": "High-Performance Laptop",
            "location": "Uyo",
            "availability": true,
            "pay-on-delivery": true,
            "fingerprint": true,
            "seller-id": "192934656",
            "seller-phone-no": "+81234567890",
            "battery-life": "12 hours"
          },
          {
            "id": 4,
            "brand": "Dell",
            "itemName": "Latitude 2X",
            "imageSrc": "../src/assets/img/laptops.jpg",
            "price": 2000000,
            "condition": "New",
            "capacity": "512GB",
            "graphics-card": "NVIDIA GeForce GTX 1660 Ti",
            "operating-system": "Windows 11",
            "touchscreen": false,
            "description": "Lorem ipsum dolor sit amet, consectetur adipiscing elit.",
            "model": "Latitude X",
            "ram": "16GB",
            "processor": "Intel Core i7",
            "display-size": "15.6 inches",
            "storage-type": "SSD",
            "colour": "Silver",
            "frame-material": "Aluminum",
            "title": "High-Performance Laptop",
            "location": "Uyo",
            "availability": true,
            "pay-on-delivery": true,
            "fingerprint": true,
            "seller-id": "192934656",
            "seller-phone-no": "+81234567890",
            "battery-life": "8 hours"
          },
          {
            "id": 5,
            "brand": "Dell",
            "itemName": "Inspiron 2XPRO",
            "imageSrc": "../src/assets/img/laptops.jpg",
            "price": 5000000,
            "condition": "New",
            "capacity": "512GB",
            "graphics-card": "NVIDIA GeForce GTX 1660 Ti",
            "operating-system": "Windows 11",
            "touchscreen": false,
            "description": "Lorem ipsum dolor sit amet, consectetur adipiscing elit.",
            "model": "Latitude X",
            "ram": "16GB",
            "processor": "Intel Core i7",
            "display-size": "15.6 inches",
            "storage-type": "SSD",
            "colour": "Silver",
            "frame-material": "Aluminum",
            "title": "High-Performance Laptop",
            "location": "Uyo",
            "availability": true,
            "pay-on-delivery": true,
            "fingerprint": true,
            "seller-id": "192934656",
            "seller-phone-no": "+81234567890",
            "battery-life": "8 hours"
          },
          {
            "id": 6,
            "brand": "Dell",
            "itemName": "Latitude Series",
            "imageSrc": "../src/assets/img/laptops.jpg",
            "price": 100000,
            "condition": "New",
            "capacity": "512GB",
            "graphics-card": "NVIDIA GeForce GTX 1660 Ti",
            "operating-system": "Windows 11",
            "touchscreen": false,
            "description": "Lorem ipsum dolor sit amet, consectetur adipiscing elit.",
            "model": "Latitude X",
            "ram": "16GB",
            "processor": "Intel Core i7",
            "display-size": "15.6 inches",
            "storage-type": "SSD",
            "colour": "Silver",
            "frame-material": "Aluminum",
            "title": "High-Performance Laptop",
            "location": "Uyo",
            "availability": true,
            "pay-on-delivery": true,
            "fingerprint": true,
            "seller-id": "192934656",
            "seller-phone-no": "+81234567890",
            "battery-life": "8 hours"
          }
      ]
    },


    {
      "category": "HP Laptops",
      "items": [
        {
          "id": 1,
          "brand": "HP",
          "itemName": "HP Pavilion",
          "imageSrc": "../src/assets/img/laptops.jpg",
          "price": 180000,
          "condition": "New",
          "capacity": "512GB",
            "graphics-card": "NVIDIA GeForce GTX 1660 Ti",
            "operating-system": "Windows 11",
            "touchscreen": false,
            "description": "Lorem ipsum dolor sit amet, consectetur adipiscing elit.",
            "model": "Latitude X",
            "ram": "16GB",
            "processor": "Intel Core i5",
            "display-size": "15.6 inches",
            "storage-type": "SSD",
            "colour": "Silver",
            "frame-material": "Aluminum",
            "title": "High-Performance Laptop",
            "location": "Uyo",
            "availability": true,
            "pay-on-delivery": true,
            "fingerprint": true,
            "seller-id": "192934656",
            "seller-phone-no": "+81234567890",
            "battery-life": "10 hours"
        },
              {
                "id": 2,
                "brand": "HP",
                "itemName": "HP Latitude",
                "imageSrc": "../src/assets/img/laptops.jpg",
                "price": 580000,
                "condition": "New",
                "capacity": "512GB",
                  "graphics-card": "NVIDIA GeForce GTX 1660 Ti",
                  "operating-system": "Windows 10",
                  "touchscreen": false,
                  "description": "Lorem ipsum dolor sit amet, consectetur adipiscing elit.",
                  "model": "Latitude X",
                  "ram": "16GB",
                  "processor": "Intel Core i5",
                  "display-size": "15.6 inches",
                  "storage-type": "SSD",
                  "colour": "Silver",
                  "frame-material": "Aluminum",
                  "title": "High-Performance Laptop",
                  "location": "Uyo",
                  "availability": true,
                  "pay-on-delivery": true,
                  "fingerprint": true,
                  "seller-id": "192934656",
                  "seller-phone-no": "+81234567890",
                  "battery-life": "10 hours"
              },
             
                  {
                    "id": 3,
                    "brand": "HP",
                    "itemName": "HP Elitebook",
                    "imageSrc": "../src/assets/img/laptops.jpg",
                    "price": 700000,
                    "condition": "New",
                    "capacity": "512GB",
                      "graphics-card": "NVIDIA GeForce GTX 1660 Ti",
                      "operating-system": "Windows 11",
                      "touchscreen": false,
                      "description": "Lorem ipsum dolor sit amet, consectetur adipiscing elit.",
                      "model": "Latitude X",
                      "ram": "16GB",
                      "processor": "Intel Core i5",
                      "display-size": "15.6 inches",
                      "storage-type": "SSD",
                      "colour": "Silver",
                      "frame-material": "Aluminum",
                      "title": "High-Performance Laptop",
                      "location": "Uyo",
                      "availability": true,
                      "pay-on-delivery": true,
                      "fingerprint": true,
                      "seller-id": "192934656",
                      "seller-phone-no": "+81234567890",
                      "battery-life": "10 hours"
                  },
            
                      {
                        "id": 4,
                        "brand": "HP",
                        "itemName": "HP Legion",
                        "imageSrc": "../src/assets/img/laptops.jpg",
                        "price": 3000000,
                        "condition": "New",
                        "capacity": "512GB",
                          "graphics-card": "NVIDIA GeForce GTX 1660 Ti",
                          "operating-system": "Windows 11",
                          "touchscreen": false,
                          "description": "Lorem ipsum dolor sit amet, consectetur adipiscing elit.",
                          "model": "Latitude X",
                          "ram": "16GB",
                          "processor": "Intel Core i5",
                          "display-size": "15.6 inches",
                          "storage-type": "SSD",
                          "colour": "Silver",
                          "frame-material": "Aluminum",
                          "title": "High-Performance Laptop",
                          "location": "Uyo",
                          "availability": true,
                          "pay-on-delivery": true,
                          "fingerprint": true,
                          "seller-id": "192934656",
                          "seller-phone-no": "+81234567890",
                          "battery-life": "16 hours"
                      },

                      {
                        "id": 5,
                        "brand": "HP",
                        "itemName": "HP ProBook",
                        "imageSrc": "../src/assets/img/laptops.jpg",
                        "price": 900000,
                        "condition": "New",
                        "capacity": "512GB",
                          "graphics-card": "NVIDIA GeForce GTX 1660 Ti",
                          "operating-system": "Windows 11",
                          "touchscreen": false,
                          "description": "Lorem ipsum dolor sit amet, consectetur adipiscing elit.",
                          "model": "Latitude X",
                          "ram": "16GB",
                          "processor": "Intel Core i5",
                          "display-size": "15.6 inches",
                          "storage-type": "SSD",
                          "colour": "Silver",
                          "frame-material": "Aluminum",
                          "title": "High-Performance Laptop",
                          "location": "Uyo",
                          "availability": true,
                          "pay-on-delivery": true,
                          "fingerprint": true,
                          "seller-id": "192934656",
                          "seller-phone-no": "+81234567890",
                          "battery-life": "10 hours"
                      },
                
                          {
                            "id": 6,
                            "brand": "HP",
                            "itemName": "HP Legion",
                            "imageSrc": "../src/assets/img/laptops.jpg",
                            "price": 650000,
                            "condition": "New",
                            "capacity": "512GB",
                              "graphics-card": "NVIDIA GeForce GTX 1660 Ti",
                              "operating-system": "Windows 11",
                              "touchscreen": false,
                              "description": "Lorem ipsum dolor sit amet, consectetur adipiscing elit.",
                              "model": "Latitude X",
                              "ram": "16GB",
                              "processor": "Intel Core i5",
                              "display-size": "15.6 inches",
                              "storage-type": "SSD",
                              "colour": "Silver",
                              "frame-material": "Aluminum",
                              "title": "High-Performance Laptop",
                              "location": "Uyo",
                              "availability": true,
                              "pay-on-delivery": true,
                              "fingerprint": true,
                              "seller-id": "192934656",
                              "seller-phone-no": "+81234567890",
                              "battery-life": "16 hours"
                          }
      ]
    },


    {
      "category": "Lenovo Laptops",
      "items": [
        {
          "id": 1,
          "brand": "Lenovo",
          "itemName": "Lenovo Pavilion",
          "imageSrc": "../src/assets/img/laptops.jpg",
          "price": 180000,
          "condition": "New",
          "capacity": "512GB",
            "graphics-card": "NVIDIA GeForce GTX 1660 Ti",
            "operating-system": "Windows 11",
            "touchscreen": false,
            "description": "Lorem ipsum dolor sit amet, consectetur adipiscing elit.",
            "model": "Latitude X",
            "ram": "16GB",
            "processor": "Intel Core i5",
            "display-size": "15.6 inches",
            "storage-type": "SSD",
            "colour": "Silver",
            "frame-material": "Aluminum",
            "title": "High-Performance Laptop",
            "location": "Uyo",
            "availability": true,
            "pay-on-delivery": true,
            "fingerprint": true,
            "seller-id": "192934656",
            "seller-phone-no": "+81234567890",
            "battery-life": "10 hours"
        },
              {
                "id": 2,
                "brand": "Lenovo",
                "itemName": "Lenovo Latitude",
                "imageSrc": "../src/assets/img/laptops.jpg",
                "price": 580000,
                "condition": "New",
                "capacity": "512GB",
                  "graphics-card": "NVIDIA GeForce GTX 1660 Ti",
                  "operating-system": "Windows 10",
                  "touchscreen": false,
                  "description": "Lorem ipsum dolor sit amet, consectetur adipiscing elit.",
                  "model": "Latitude X",
                  "ram": "16GB",
                  "processor": "Intel Core i5",
                  "display-size": "15.6 inches",
                  "storage-type": "SSD",
                  "colour": "Silver",
                  "frame-material": "Aluminum",
                  "title": "High-Performance Laptop",
                  "location": "Uyo",
                  "availability": true,
                  "pay-on-delivery": true,
                  "fingerprint": true,
                  "seller-id": "192934656",
                  "seller-phone-no": "+81234567890",
                  "battery-life": "10 hours"
              },
             
                  {
                    "id": 3,
                    "brand": "Lenovo",
                    "itemName": "Lenovo Elitebook",
                    "imageSrc": "../src/assets/img/laptops.jpg",
                    "price": 700000,
                    "condition": "New",
                    "capacity": "512GB",
                      "graphics-card": "NVIDIA GeForce GTX 1660 Ti",
                      "operating-system": "Windows 11",
                      "touchscreen": false,
                      "description": "Lorem ipsum dolor sit amet, consectetur adipiscing elit.",
                      "model": "Latitude X",
                      "ram": "16GB",
                      "processor": "Intel Core i5",
                      "display-size": "15.6 inches",
                      "storage-type": "SSD",
                      "colour": "Silver",
                      "frame-material": "Aluminum",
                      "title": "High-Performance Laptop",
                      "location": "Uyo",
                      "availability": true,
                      "pay-on-delivery": true,
                      "fingerprint": true,
                      "seller-id": "192934656",
                      "seller-phone-no": "+81234567890",
                      "battery-life": "10 hours"
                  },
            
                      {
                        "id": 4,
                        "brand": "Lenovo",
                        "itemName": "Lenovo Legion",
                        "imageSrc": "../src/assets/img/laptops.jpg",
                        "price": 3000000,
                        "condition": "New",
                        "capacity": "512GB",
                          "graphics-card": "NVIDIA GeForce GTX 1660 Ti",
                          "operating-system": "Windows 11",
                          "touchscreen": false,
                          "description": "Lorem ipsum dolor sit amet, consectetur adipiscing elit.",
                          "model": "Latitude X",
                          "ram": "16GB",
                          "processor": "Intel Core i5",
                          "display-size": "15.6 inches",
                          "storage-type": "SSD",
                          "colour": "Silver",
                          "frame-material": "Aluminum",
                          "title": "High-Performance Laptop",
                          "location": "Uyo",
                          "availability": true,
                          "pay-on-delivery": true,
                          "fingerprint": true,
                          "seller-id": "192934656",
                          "seller-phone-no": "+81234567890",
                          "battery-life": "16 hours"
                      },


                      {
                        "id": 5,
                        "brand": "Lenovo",
                        "itemName": "Lenovo Elitebook",
                        "imageSrc": "../src/assets/img/laptops.jpg",
                        "price": 700000,
                        "condition": "New",
                        "capacity": "512GB",
                          "graphics-card": "NVIDIA GeForce GTX 1660 Ti",
                          "operating-system": "Windows 11",
                          "touchscreen": false,
                          "description": "Lorem ipsum dolor sit amet, consectetur adipiscing elit.",
                          "model": "Latitude X",
                          "ram": "16GB",
                          "processor": "Intel Core i5",
                          "display-size": "15.6 inches",
                          "storage-type": "SSD",
                          "colour": "Silver",
                          "frame-material": "Aluminum",
                          "title": "High-Performance Laptop",
                          "location": "Uyo",
                          "availability": true,
                          "pay-on-delivery": true,
                          "fingerprint": true,
                          "seller-id": "192934656",
                          "seller-phone-no": "+81234567890",
                          "battery-life": "10 hours"
                      },
                
                          {
                            "id": 6,
                            "brand": "Lenovo",
                            "itemName": "Lenovo Legion",
                            "imageSrc": "../src/assets/img/laptops.jpg",
                            "price": 3000000,
                            "condition": "New",
                            "capacity": "512GB",
                              "graphics-card": "NVIDIA GeForce GTX 1660 Ti",
                              "operating-system": "Windows 11",
                              "touchscreen": false,
                              "description": "Lorem ipsum dolor sit amet, consectetur adipiscing elit.",
                              "model": "Latitude X",
                              "ram": "16GB",
                              "processor": "Intel Core i5",
                              "display-size": "15.6 inches",
                              "storage-type": "SSD",
                              "colour": "Silver",
                              "frame-material": "Aluminum",
                              "title": "High-Performance Laptop",
                              "location": "Uyo",
                              "availability": true,
                              "pay-on-delivery": true,
                              "fingerprint": true,
                              "seller-id": "192934656",
                              "seller-phone-no": "+81234567890",
                              "battery-life": "16 hours"
                          }
          ]
      
    },



    {
      "category": "Toshiba Laptops",
      "items": [
        {
          "id": 1,
          "brand": "Toshiba",
          "itemName": "Toshiba Pavilion",
          "imageSrc": "../src/assets/img/laptops.jpg",
          "price": 180000,
          "condition": "New",
          "capacity": "512GB",
            "graphics-card": "NVIDIA GeForce GTX 1660 Ti",
            "operating-system": "Windows 11",
            "touchscreen": false,
            "description": "Lorem ipsum dolor sit amet, consectetur adipiscing elit.",
            "model": "Latitude X",
            "ram": "16GB",
            "processor": "Intel Core i5",
            "display-size": "15.6 inches",
            "storage-type": "SSD",
            "colour": "Silver",
            "frame-material": "Aluminum",
            "title": "High-Performance Laptop",
            "location": "Uyo",
            "availability": true,
            "pay-on-delivery": true,
            "fingerprint": true,
            "seller-id": "192934656",
            "seller-phone-no": "+81234567890",
            "battery-life": "10 hours"
        },
              {
                "id": 2,
                "brand": "Toshiba",
                "itemName": "Toshiba Latitude",
                "imageSrc": "../src/assets/img/laptops.jpg",
                "price": 580000,
                "condition": "New",
                "capacity": "512GB",
                  "graphics-card": "NVIDIA GeForce GTX 1660 Ti",
                  "operating-system": "Windows 10",
                  "touchscreen": false,
                  "description": "Lorem ipsum dolor sit amet, consectetur adipiscing elit.",
                  "model": "Latitude X",
                  "ram": "16GB",
                  "processor": "Intel Core i5",
                  "display-size": "15.6 inches",
                  "storage-type": "SSD",
                  "colour": "Silver",
                  "frame-material": "Aluminum",
                  "title": "High-Performance Laptop",
                  "location": "Uyo",
                  "availability": true,
                  "pay-on-delivery": true,
                  "fingerprint": true,
                  "seller-id": "192934656",
                  "seller-phone-no": "+81234567890",
                  "battery-life": "10 hours"
              },
             
                  {
                    "id": 3,
                    "brand": "Toshiba",
                    "itemName": "Toshiba Elitebook",
                    "imageSrc": "../src/assets/img/laptops.jpg",
                    "price": 700000,
                    "condition": "New",
                    "capacity": "512GB",
                      "graphics-card": "NVIDIA GeForce GTX 1660 Ti",
                      "operating-system": "Windows 11",
                      "touchscreen": false,
                      "description": "Lorem ipsum dolor sit amet, consectetur adipiscing elit.",
                      "model": "Latitude X",
                      "ram": "16GB",
                      "processor": "Intel Core i5",
                      "display-size": "15.6 inches",
                      "storage-type": "SSD",
                      "colour": "Silver",
                      "frame-material": "Aluminum",
                      "title": "High-Performance Laptop",
                      "location": "Uyo",
                      "availability": true,
                      "pay-on-delivery": true,
                      "fingerprint": true,
                      "seller-id": "192934656",
                      "seller-phone-no": "+81234567890",
                      "battery-life": "10 hours"
                  },
            
                      {
                        "id": 4,
                        "brand": "Toshiba",
                        "itemName": "Toshiba Legion",
                        "imageSrc": "../src/assets/img/laptops.jpg",
                        "price": 3000000,
                        "condition": "New",
                        "capacity": "512GB",
                          "graphics-card": "NVIDIA GeForce GTX 1660 Ti",
                          "operating-system": "Windows 11",
                          "touchscreen": false,
                          "description": "Lorem ipsum dolor sit amet, consectetur adipiscing elit.",
                          "model": "Latitude X",
                          "ram": "16GB",
                          "processor": "Intel Core i5",
                          "display-size": "15.6 inches",
                          "storage-type": "SSD",
                          "colour": "Silver",
                          "frame-material": "Aluminum",
                          "title": "High-Performance Laptop",
                          "location": "Uyo",
                          "availability": true,
                          "pay-on-delivery": true,
                          "fingerprint": true,
                          "seller-id": "192934656",
                          "seller-phone-no": "+81234567890",
                          "battery-life": "16 hours"
                      },


                      {
                        "id": 5,
                        "brand": "Toshiba",
                        "itemName": "Toshiba Notebook",
                        "imageSrc": "../src/assets/img/laptops.jpg",
                        "price": 750000,
                        "condition": "New",
                        "capacity": "512GB",
                          "graphics-card": "NVIDIA GeForce GTX 1660 Ti",
                          "operating-system": "Windows 11",
                          "touchscreen": false,
                          "description": "Lorem ipsum dolor sit amet, consectetur adipiscing elit.",
                          "model": "Latitude X",
                          "ram": "16GB",
                          "processor": "Intel Core i5",
                          "display-size": "15.6 inches",
                          "storage-type": "SSD",
                          "colour": "Silver",
                          "frame-material": "Aluminum",
                          "title": "High-Performance Laptop",
                          "location": "Uyo",
                          "availability": true,
                          "pay-on-delivery": true,
                          "fingerprint": true,
                          "seller-id": "192934656",
                          "seller-phone-no": "+81234567890",
                          "battery-life": "10 hours"
                      },
                
                          {
                            "id": 6,
                            "brand": "Toshiba",
                            "itemName": "Toshiba Legion Pro",
                            "imageSrc": "../src/assets/img/laptops.jpg",
                            "price": 700000,
                            "condition": "New",
                            "capacity": "512GB",
                              "graphics-card": "NVIDIA GeForce GTX 1660 Ti",
                              "operating-system": "Windows 11",
                              "touchscreen": false,
                              "description": "Lorem ipsum dolor sit amet, consectetur adipiscing elit.",
                              "model": "Latitude X",
                              "ram": "16GB",
                              "processor": "Intel Core i5",
                              "display-size": "15.6 inches",
                              "storage-type": "SSD",
                              "colour": "Silver",
                              "frame-material": "Aluminum",
                              "title": "High-Performance Laptop",
                              "location": "Uyo",
                              "availability": true,
                              "pay-on-delivery": true,
                              "fingerprint": true,
                              "seller-id": "192934656",
                              "seller-phone-no": "+81234567890",
                              "battery-life": "16 hours"
                          }
      ]
    }
  ]
  